{
  "name": "ManufacturingOperationTaskSearchRow",
  "type": "complexType",
  "file": "lists.supplyChain.xsd",
  "extends": "SearchRow",
  "extendsNamespace": "platformCore",
  "elements": {
    "basic": {
      "name": "basic",
      "type": "ManufacturingOperationTaskSearchRowBasic",
      "minOccurs": "0",
      "typeNamespace": "platformCommon"
    },
    "predecessorJoin": {
      "name": "predecessorJoin",
      "type": "ManufacturingOperationTaskSearchRowBasic",
      "minOccurs": "0",
      "typeNamespace": "platformCommon"
    },
    "userJoin": {
      "name": "userJoin",
      "type": "EmployeeSearchRowBasic",
      "minOccurs": "0",
      "typeNamespace": "platformCommon"
    },
    "workOrderJoin": {
      "name": "workOrderJoin",
      "type": "TransactionSearchRowBasic",
      "minOccurs": "0",
      "typeNamespace": "platformCommon"
    },
    "customSearchJoin": {
      "name": "customSearchJoin",
      "type": "CustomSearchRowBasic",
      "minOccurs": "0",
      "maxOccurs": "unbounded",
      "typeNamespace": "platformCommon"
    }
  }
}