{
  "name": "PaycheckJournal",
  "type": "complexType",
  "file": "transactions.employees.xsd",
  "extends": "Record",
  "extendsNamespace": "platformCore",
  "elements": {
    "subsidiary": {
      "name": "subsidiary",
      "type": "RecordRef",
      "minOccurs": "0",
      "typeNamespace": "platformCore"
    },
    "currency": {
      "name": "currency",
      "type": "RecordRef",
      "minOccurs": "0",
      "typeNamespace": "platformCore"
    },
    "exchangeRate": {
      "name": "exchangeRate",
      "type": "double",
      "minOccurs": "0",
      "typeNamespace": "xsd"
    },
    "createdDate": {
      "name": "createdDate",
      "type": "dateTime",
      "minOccurs": "0",
      "typeNamespace": "xsd"
    },
    "lastModifiedDate": {
      "name": "lastModifiedDate",
      "type": "dateTime",
      "minOccurs": "0",
      "typeNamespace": "xsd"
    },
    "customForm": {
      "name": "customForm",
      "type": "RecordRef",
      "minOccurs": "0",
      "typeNamespace": "platformCore"
    },
    "tranId": {
      "name": "tranId",
      "type": "string",
      "minOccurs": "0",
      "typeNamespace": "xsd"
    },
    "employee": {
      "name": "employee",
      "type": "RecordRef",
      "minOccurs": "0",
      "typeNamespace": "platformCore"
    },
    "tranDate": {
      "name": "tranDate",
      "type": "dateTime",
      "minOccurs": "0",
      "typeNamespace": "xsd"
    },
    "postingPeriod": {
      "name": "postingPeriod",
      "type": "RecordRef",
      "minOccurs": "0",
      "typeNamespace": "platformCore"
    },
    "account": {
      "name": "account",
      "type": "RecordRef",
      "minOccurs": "0",
      "typeNamespace": "platformCore"
    },
    "department": {
      "name": "department",
      "type": "RecordRef",
      "minOccurs": "0",
      "typeNamespace": "platformCore"
    },
    "class": {
      "name": "class",
      "type": "RecordRef",
      "minOccurs": "0",
      "typeNamespace": "platformCore"
    },
    "location": {
      "name": "location",
      "type": "RecordRef",
      "minOccurs": "0",
      "typeNamespace": "platformCore"
    },
    "companyContributionList": {
      "name": "companyContributionList",
      "type": "PaycheckJournalCompanyContributionList",
      "minOccurs": "0",
      "typeNamespace": "tranEmp"
    },
    "deductionList": {
      "name": "deductionList",
      "type": "PaycheckJournalDeductionList",
      "minOccurs": "0",
      "typeNamespace": "tranEmp"
    },
    "employeeTaxList": {
      "name": "employeeTaxList",
      "type": "PaycheckJournalEmployeeTaxList",
      "minOccurs": "0",
      "typeNamespace": "tranEmp"
    },
    "companyTaxList": {
      "name": "companyTaxList",
      "type": "PaycheckJournalCompanyTaxList",
      "minOccurs": "0",
      "typeNamespace": "tranEmp"
    },
    "earningList": {
      "name": "earningList",
      "type": "PaycheckJournalEarningList",
      "minOccurs": "0",
      "typeNamespace": "tranEmp"
    },
    "customFieldList": {
      "name": "customFieldList",
      "type": "CustomFieldList",
      "minOccurs": "0",
      "typeNamespace": "platformCore"
    }
  },
  "attributes": {
    "internalId": {
      "name": "internalId",
      "type": "string",
      "typeNamespace": "xsd"
    },
    "externalId": {
      "name": "externalId",
      "type": "string",
      "typeNamespace": "xsd"
    }
  }
}